kuramoto_util/__init__.py
kuramoto_util/core/__init__.py
kuramoto_util/core/_core.py
kuramoto_util/dynamics/__init__.py
kuramoto_util/dynamics/_dynamics.py
kuramoto_util/legacy/__init__.py
kuramoto_util/legacy/common.py
kuramoto_util/legacy/hdfutil.py
kuramoto_util/legacy/km2d.py
kuramoto_util/legacy/math.py
kuramoto_util/math/__init__.py
kuramoto_util/math/math.py
kuramoto_util/sampling/__init__.py
kuramoto_util/sampling/_sampling.py
kuramoto_util/storage/__init__.py
kuramoto_util/storage/_storage.py
kuramoto_util/weights/__init__.py
kuramoto_util/weights/_weights.py
kuramoto_util-0.0.3.dist-info/LICENSE
kuramoto_util-0.0.3.dist-info/METADATA
kuramoto_util-0.0.3.dist-info/WHEEL
kuramoto_util-0.0.3.dist-info/top_level.txt
kuramoto_util-0.0.3.dist-info/RECORD
