Metadata-Version: 2.1
Name: kuramoto-util
Version: 0.0.3
Summary: package for Kuramoto model simulations
Home-page: https://github.com/michael-960/kuramoto_util
Author: Michael Wang
Author-email: mike.wang96029@gmail.com
Project-URL: Bug Tracker, https://github.com/michael-960/kuramoto_util/issues
Classifier: Programming Language :: Python :: 3
Classifier: License :: OSI Approved :: MIT License
Classifier: Operating System :: OS Independent
Requires-Python: >=3.7
License-File: LICENSE
Requires-Dist: numpy (>=1.21.2)
Requires-Dist: scipy (>=1.7)
Requires-Dist: pyfftw (>=0.12)
Requires-Dist: matplotlib (>=3.5.1)
Requires-Dist: michael960-lib (>=0.1.4)
Requires-Dist: torusgrid (>=0.3.1)
Requires-Dist: h5py (>=3.0.0)
